{
  "ProjectName": "WPFStyles",
  "Title": "WPF : Styling a Combobox, Button and a TabItem",
  "Description": "WPF Styles project shows how to create styles for Combobox, Tabltem and Button. Ready to use styles. Can be modified. Created in VB.net(loading the style file).\n",
  "MovedLink": "",
  "HomeWiki": "<div class=\"wikidoc\"><b>Project Description</b><br />WPF Styles project shows how to create styles for Combobox, Tabltem and Button. Ready to use styles. Can be modified. Created in VB.net&#40;loading the style file&#41;.<br /><br /><br /><b>Summary</b><br /><br />This project is solely made for the purpose of sharing  WPF Styles so that one doesn&#39;t have to fight hard for setting up styles like I had to. I am not highly skilled in WPF, but somehow I managed to create few styles. I thought to share it with community and it could save time for bunch of people. Suggestions are <b>WELCOME</b>.<br /><br /><a href=\"http://excelnoob.blogspot.com/2009/08/wpf-styling-combobox-button-and.html\">Click here for details and screenshot</a><br /><br />Thanks,<br />Vikas<br /><a href=\"http://excelnoob.blogspot.com\">http://excelnoob.blogspot.com</a></div><div class=\"ClearBoth\"></div>",
  "TagList": "WPF,Styles,Combobox,Tab Item,Button,Tab Item Style,Combobox Style,Button Style,WPF Styles,Combobox template,",
  "LastEdited": "2009-08-12T04:27:19.983-07:00"
}