{
  "ProjectName": "Blacklight",
  "Title": "Blacklight Toolkit",
  "Description": "Blacklight controls are a suite of controls for Silverlight and WPF.\r\nIncludes Dashboard.",
  "MovedLink": "",
  "HomeWiki": "<div class=\"wikidoc\"><b>Project Description</b><br />Blacklight controls are a suite of controls for Silverlight and WPF.<br />Includes Dashboard.<br /><img src=\"http://blender3dlive.com/images/dashboard.png\" /><br />Silverlight Project?<br /><a href=\"http://www.blender3dlive.com\">http://www.blender3dlive.com</a></div><div class=\"ClearBoth\"></div>",
  "TagList": "Silverlight Controls,WPF controls,Dashboard,",
  "LastEdited": "2012-05-24T19:02:20.11-07:00"
}