{
  "ProjectName": "openapp",
  "Title": "Open Application",
  "Description": "OpenApp 是为了在 SNS 时代而启动的项目，我们希望在 SNS 领域提供一个基于 Silverlight 技术构建的组件集合平台，提供各种应用，特别是在企业应用领域，提供各种 App 来满足客户的需要。\n我们将在电子商务进行重点投入，并且利用我们多年的企业内容管理（ECM）方面的专业知识结合，为未来的电子商务市场提供我们的方案。",
  "MovedLink": "",
  "HomeWiki": "<div class=\"wikidoc\">OpenApp 是为了在 SNS 时代而启动的项目，我们希望在 SNS 领域提供一个基于 Silverlight 技术构建的组件集合平台，提供各种应用，特别是在企业应用领域，提供各种 App 来满足客户的需要。<br />我们将在电子商务进行重点投入，并且利用我们多年的企业内容管理（ECM）方面的专业知识结合，为未来的电子商务市场提供我们的方案。<br /></div><div class=\"ClearBoth\"></div>",
  "TagList": "",
  "LastEdited": "2009-10-18T04:10:03.59-07:00"
}