{
  "ProjectName": "clientidless",
  "Title": "ASP.NET without ClientID's",
  "Description": "Render ASP.NET Controls without ClientID - reduce HTML output response",
  "MovedLink": "",
  "HomeWiki": "<div class=\"wikidoc\">\r\n<p><strong>Project Description</strong><br>\r\nASP.NET 4 brings some kind of control over <em>ClientID</em> rendering. Developers can define how exactly\r\n<em>ClientID</em> will be rendered but have no possibility to turn it off.</p>\r\n<p>Almost all the time when developer works with <em>Panels</em>, <em>Labels</em>,\r\n<em>HyperLinks</em>, <em>Images</em>, <em>Tables</em> and so on, he needs only <em>\r\nserver ID</em> to interact with control on server side but will never use its <em>\r\nClientID</em> on Client Side. The problem is that this <em>ClientID</em> will be rendered in any case, even if nobody use it. As result - bigger HTML output size with a lot of unnecessary IDs.</p>\r\n<p><strong>This Project allows to turn off ClientID rendering for each control in any ASP.NET\r\n<span style=\"color:#ff0000\">2.0&#43;</span> Project and reduce output Page Size a lot.</strong><br>\r\nException is only for Controls that may cause <em>PostBack</em>. The reason for that -\r\n<em>ClientID(UniqueID)</em> is used in <em>PostBack</em> mechanism. Also, interactive controls have high chances to be accessed from Client Side (example: button click by JavaScript code)</p>\r\n<p><strong>Demo:</strong> <a title=\"http://show-demos.net/NoClientId\" href=\"http://show-demos.net/NoClientId\">\r\nhttp://show-demos.net/NoClientId</a></p>\r\n<p><strong>Output HTML example:</strong><br>\r\n<span style=\"color:#888888\"><strong>with ClientIDs (standard ASP.NET output):</strong></span></p>\r\n<div style=\"color:black; background-color:white\">\r\n<pre><span style=\"color:blue\">&lt;</span><span style=\"color:#a31515\">div</span> <span style=\"text-decoration:underline\"><span style=\"color:red\">id</span><span style=\"color:blue\">=</span><span style=\"color:blue\">&quot;repeater_ctl00_mainPanel&quot;</span></span> <span style=\"color:red\">class</span><span style=\"color:blue\">=</span><span style=\"color:blue\">&quot;panel&quot;</span><span style=\"color:blue\">&gt;</span>\n  <span style=\"color:blue\">&lt;</span><span style=\"color:#a31515\">div</span> <span style=\"text-decoration:underline\"><span style=\"color:red\">id</span><span style=\"color:blue\">=</span><span style=\"color:blue\">&quot;repeater_ctl00_childPanel&quot;</span></span><span style=\"color:blue\">&gt;</span>\n    <span style=\"color:blue\">&lt;</span><span style=\"color:#a31515\">div</span> <span style=\"text-decoration:underline\"><span style=\"color:red\">id</span><span style=\"color:blue\">=</span><span style=\"color:blue\">&quot;repeater_ctl00_oneMorePanel&quot;</span></span><span style=\"color:blue\">&gt;</span>\n      <span style=\"color:blue\">&lt;</span><span style=\"color:#a31515\">span</span> <span style=\"text-decoration:underline\"><span style=\"color:red\">id</span><span style=\"color:blue\">=</span><span style=\"color:blue\">&quot;repeater_ctl00_someLabel&quot;</span></span><span style=\"color:blue\">&gt;</span>Top Label<span style=\"color:blue\">&lt;/</span><span style=\"color:#a31515\">span</span><span style=\"color:blue\">&gt;</span><span style=\"color:blue\">&lt;</span><span style=\"color:#a31515\">br</span> <span style=\"color:blue\">/&gt;</span>\n        <span style=\"color:blue\">&lt;</span><span style=\"color:#a31515\">a</span> <span style=\"text-decoration:underline\"><span style=\"color:red\">id</span><span style=\"color:blue\">=</span><span style=\"color:blue\">&quot;repeater_ctl00_hyperLink&quot;</span></span> <span style=\"color:red\">href</span><span style=\"color:blue\">=</span><span style=\"color:blue\">&quot;http://asp.net&quot;</span><span style=\"color:blue\">&gt;</span>\n        <span style=\"color:blue\">&lt;</span><span style=\"color:#a31515\">img</span> <span style=\"text-decoration:underline\"><span style=\"color:red\">id</span><span style=\"color:blue\">=</span><span style=\"color:blue\">&quot;repeater_ctl00_someImage&quot;</span></span> <span style=\"color:red\">src</span><span style=\"color:blue\">=</span><span style=\"color:blue\">&quot;/img/img.png&quot;</span> <span style=\"color:red\">style</span><span style=\"color:blue\">=</span><span style=\"color:blue\">&quot;border-width:0px;&quot;</span> <span style=\"color:blue\">/&gt;</span><span style=\"color:blue\">&lt;</span><span style=\"color:#a31515\">br</span> <span style=\"color:blue\">/&gt;</span>\n        <span style=\"color:blue\">&lt;</span><span style=\"color:#a31515\">table</span> <span style=\"text-decoration:underline\"><span style=\"color:red\">id</span><span style=\"color:blue\">=</span><span style=\"color:blue\">&quot;repeater_ctl00_table&quot;</span></span> <span style=\"color:red\">border</span><span style=\"color:blue\">=</span><span style=\"color:blue\">&quot;0&quot;</span><span style=\"color:blue\">&gt;</span>\n          <span style=\"color:blue\">&lt;</span><span style=\"color:#a31515\">tr</span> <span style=\"text-decoration:underline\"><span style=\"color:red\">id</span><span style=\"color:blue\">=</span><span style=\"color:blue\">&quot;repeater_ctl00_headerRow&quot;</span></span><span style=\"color:blue\">&gt;</span>\n            <span style=\"color:blue\">&lt;</span><span style=\"color:#a31515\">th</span> <span style=\"text-decoration:underline\"><span style=\"color:red\">id</span><span style=\"color:blue\">=</span><span style=\"color:blue\">&quot;repeater_ctl00_headerCell&quot;</span></span><span style=\"color:blue\">&gt;</span>\n              <span style=\"color:blue\">&lt;</span><span style=\"color:#a31515\">span</span> <span style=\"text-decoration:underline\"><span style=\"color:red\">id</span><span style=\"color:blue\">=</span><span style=\"color:blue\">&quot;repeater_ctl00_label&quot;</span></span><span style=\"color:blue\">&gt;</span>Test<span style=\"color:blue\">&lt;/</span><span style=\"color:#a31515\">span</span><span style=\"color:blue\">&gt;</span>\n            <span style=\"color:blue\">&lt;/</span><span style=\"color:#a31515\">th</span><span style=\"color:blue\">&gt;</span>\n          <span style=\"color:blue\">&lt;/</span><span style=\"color:#a31515\">tr</span><span style=\"color:blue\">&gt;</span>\n        <span style=\"color:blue\">&lt;/</span><span style=\"color:#a31515\">table</span><span style=\"color:blue\">&gt;</span>\n        <span style=\"color:blue\">&lt;</span><span style=\"color:#a31515\">a</span> <span style=\"text-decoration:underline\"><span style=\"color:red\">id</span><span style=\"color:blue\">=</span><span style=\"color:blue\">&quot;repeater_ctl00_button&quot;</span></span> <span style=\"color:red\">href</span><span style=\"color:blue\">=</span><span style=\"color:blue\">&quot;javascript:__doPostBack(&amp;#39;repeater$ctl00$button&amp;#39;,&amp;#39;&amp;#39;)&quot;</span><span style=\"color:blue\">&gt;</span>LinkButton<span style=\"color:blue\">&lt;/</span><span style=\"color:#a31515\">a</span><span style=\"color:blue\">&gt;</span><span style=\"color:blue\">&lt;/</span><span style=\"color:#a31515\">a</span><span style=\"color:blue\">&gt;</span>\n      <span style=\"color:blue\">&lt;/</span><span style=\"color:#a31515\">div</span><span style=\"color:blue\">&gt;</span>\n    <span style=\"color:blue\">&lt;/</span><span style=\"color:#a31515\">div</span><span style=\"color:blue\">&gt;</span>\n<span style=\"color:blue\">&lt;/</span><span style=\"color:#a31515\">div</span><span style=\"color:blue\">&gt;</span>\n</pre>\r\n</div>\r\n<p><span style=\"color:#888888\"><strong>without ClientIDs:</strong></span></p>\r\n<div style=\"color:black; background-color:white\">\r\n<pre><span style=\"color:blue\">&lt;</span><span style=\"color:#a31515\">div</span> <span style=\"color:red\">class</span><span style=\"color:blue\">=</span><span style=\"color:blue\">&quot;panel&quot;</span><span style=\"color:blue\">&gt;</span>\n  <span style=\"color:blue\">&lt;</span><span style=\"color:#a31515\">div</span><span style=\"color:blue\">&gt;</span>\n    <span style=\"color:blue\">&lt;</span><span style=\"color:#a31515\">div</span><span style=\"color:blue\">&gt;</span>\n      <span style=\"color:blue\">&lt;</span><span style=\"color:#a31515\">span</span><span style=\"color:blue\">&gt;</span>Top Label<span style=\"color:blue\">&lt;/</span><span style=\"color:#a31515\">span</span><span style=\"color:blue\">&gt;</span><span style=\"color:blue\">&lt;</span><span style=\"color:#a31515\">br</span> <span style=\"color:blue\">/&gt;</span>\n      <span style=\"color:blue\">&lt;</span><span style=\"color:#a31515\">a</span> <span style=\"color:red\">href</span><span style=\"color:blue\">=</span><span style=\"color:blue\">&quot;http://asp.net&quot;</span><span style=\"color:blue\">&gt;</span>\n        <span style=\"color:blue\">&lt;</span><span style=\"color:#a31515\">img</span> <span style=\"color:red\">src</span><span style=\"color:blue\">=</span><span style=\"color:blue\">&quot;/img/img.png&quot;</span> <span style=\"color:red\">style</span><span style=\"color:blue\">=</span><span style=\"color:blue\">&quot;border-width:0px;&quot;</span> <span style=\"color:blue\">/&gt;</span><span style=\"color:blue\">&lt;</span><span style=\"color:#a31515\">br</span> <span style=\"color:blue\">/&gt;</span>\n        <span style=\"color:blue\">&lt;</span><span style=\"color:#a31515\">table</span> <span style=\"color:red\">border</span><span style=\"color:blue\">=</span><span style=\"color:blue\">&quot;0&quot;</span><span style=\"color:blue\">&gt;</span>\n          <span style=\"color:blue\">&lt;</span><span style=\"color:#a31515\">tr</span><span style=\"color:blue\">&gt;</span>\n            <span style=\"color:blue\">&lt;</span><span style=\"color:#a31515\">th</span><span style=\"color:blue\">&gt;</span>\n              <span style=\"color:blue\">&lt;</span><span style=\"color:#a31515\">span</span><span style=\"color:blue\">&gt;</span>Test<span style=\"color:blue\">&lt;/</span><span style=\"color:#a31515\">span</span><span style=\"color:blue\">&gt;</span>\n            <span style=\"color:blue\">&lt;/</span><span style=\"color:#a31515\">th</span><span style=\"color:blue\">&gt;</span>\n          <span style=\"color:blue\">&lt;/</span><span style=\"color:#a31515\">tr</span><span style=\"color:blue\">&gt;</span>\n        <span style=\"color:blue\">&lt;/</span><span style=\"color:#a31515\">table</span><span style=\"color:blue\">&gt;</span>\n        <span style=\"color:blue\">&lt;</span><span style=\"color:#a31515\">a</span> <span style=\"color:red\">id</span><span style=\"color:blue\">=</span><span style=\"color:blue\">&quot;repeater_ctl01_button&quot;</span> <span style=\"color:red\">href</span><span style=\"color:blue\">=</span><span style=\"color:blue\">&quot;javascript:__doPostBack(&amp;#39;repeater$ctl01$button&amp;#39;,&amp;#39;&amp;#39;)&quot;</span><span style=\"color:blue\">&gt;</span>LinkButton<span style=\"color:blue\">&lt;/</span><span style=\"color:#a31515\">a</span><span style=\"color:blue\">&gt;</span>\n      <span style=\"color:blue\">&lt;/</span><span style=\"color:#a31515\">a</span><span style=\"color:blue\">&gt;</span>\n    <span style=\"color:blue\">&lt;/</span><span style=\"color:#a31515\">div</span><span style=\"color:blue\">&gt;</span>\n  <span style=\"color:blue\">&lt;/</span><span style=\"color:#a31515\">div</span><span style=\"color:blue\">&gt;</span>\n<span style=\"color:blue\">&lt;/</span><span style=\"color:#a31515\">div</span><span style=\"color:blue\">&gt;</span>\n</pre>\r\n</div>\r\n<p>As you can see <strong>repeater_ctl01_button</strong> still have <em>ClientID</em>. This is expected because it's a\r\n<em>LinkButton</em> - PostBack Control. PostBack controls should have ClientID to work properly.</p>\r\n</div><div class=\"ClearBoth\"></div>",
  "TagList": "rendering,Client,ClientID,Optimization,ASP.NET,",
  "LastEdited": "2011-06-08T05:41:02.59-07:00"
}