{
  "ProjectName": "eGridMSSurface",
  "Title": "eGrid on MS Surface",
  "Description": "eGrid is a multi-touch multi-user digital tabletop application for browsing and managing maps. It is useful for control room operations of utility companies. Browsing and annotating maps by different users is easy using eGrid on an interactive digital tabletop, such as MS Surface",
  "MovedLink": "",
  "HomeWiki": "<div class=\"wikidoc\"><b>Project Description</b><br />eGrid is a multi-touch multi-user digital tabletop application for browsing and managing maps. It is useful for control room operations of utility companies. Browsing and annotating maps by different users is easy using eGrid on an interactive digital tabletop, such as MS Surface<br /><br /><br /></div><div class=\"ClearBoth\"></div>",
  "TagList": "",
  "LastEdited": "2010-01-06T12:11:22.157-08:00"
}