{
  "ProjectName": "HomeUX",
  "Title": "HomeUX",
  "Description": "HomeUX is home control software featuring a Silverlight-based touch screen user interface.",
  "MovedLink": "",
  "HomeWiki": "<div class=\"wikidoc\"><b>Project Description</b><br />HomeUX is home control software featuring a Silverlight-based touch screen user interface.<br /><br />For more information about HomeUX, see the companion web site: <a href=\"http://www.HomeUX.org\">http://www.HomeUX.org</a><br /></div><div class=\"ClearBoth\"></div>",
  "TagList": "",
  "LastEdited": "2010-03-12T08:06:56.023-08:00"
}