{
  "ProjectName": "launchpoint",
  "Title": "LaunchPoint",
  "Description": "LaunchPoint is a framework for rapidly developing powerful smartclient application built on top of WPF technologies.  It provided such features as workflow driven user interface, a powerful plug-in model, 3 tier client server topology, peer to peer, update capabilities, and a simple API for adding more features as needed.",
  "MovedLink": "",
  "HomeWiki": "<div class=\"wikidoc\"><b>Project Description</b><br />LaunchPoint is a framework for rapidly developing powerful smartclient application built on top of WPF technologies.  It provided such features as workflow driven user interface, a powerful plug-in model, 3 tier client server topology, peer to peer, update capabilities, and a simple API for adding more features as needed.<br /><br /><br /></div><div class=\"ClearBoth\"></div>",
  "TagList": "wpf,",
  "LastEdited": "2008-04-16T13:47:23.49-07:00"
}