{
  "ProjectName": "mytimelinebr",
  "Title": "My Time Line Task Control",
  "Description": "Controle de Tarefas em formato de linha de tempo (time line), com Workflow e gerenciamento de permissões Grupo/Area/SubArea (www.mytimeline.com.br)",
  "MovedLink": "",
  "HomeWiki": "<div class=\"wikidoc\"><b>My Time Line</b><br />{Gerenciar Tarefas no formato Timeline}<br /><br /><br />Gerencia Tarefas de um Grupo/AreaSubArea mostrando no formato de timeline (linha de tempo), mostrando sobreposi&#231;&#245;es com controle de aprova&#231;&#227;o.<br />Um pouco de Workflow</div><div class=\"ClearBoth\"></div>",
  "TagList": "",
  "LastEdited": "2013-01-06T10:47:35-08:00"
}