{
  "ProjectName": "netscope",
  "Title": "NetScope The Network Manager",
  "Description": "NetScope is a manager for your networks. This software can disccovers, controls and monitors your LAN PCs.\n\nIt's designed to be clear for learners, fast to users and light on machines.\n\nDelivered by C#, WMI and WCF.",
  "MovedLink": "",
  "HomeWiki": "<div class=\"wikidoc\"><b>Project Description</b><br />NetScope is a manager for your networks. This software can disccovers, controls and monitors your LAN PCs.<br /><br />It&#39;s designed to be clear for learners, fast to users and light on machines.<br /><br />Delivered by C&#35;, WMI and WCF.<br /></div><div class=\"ClearBoth\"></div>",
  "TagList": "",
  "LastEdited": "2010-07-03T06:58:04.153-07:00"
}