{
  "ProjectName": "tagcloudcontrol",
  "Title": "Tag Cloud Control for asp.net",
  "Description": "Tag Cloud Control for asp.net allows the user to display the most important keywords to display in tag cloud. Each Tag has it own navigation url to navigate to a certain page.",
  "MovedLink": "",
  "HomeWiki": "<div class=\"wikidoc\"><b>Project Description</b><br />Tag Cloud Control for asp.net allows the user to display the most important keywords to display in tag cloud. Each Tag has it own navigation url to navigate to a certain page.<br /><br /><br />Visit http://www.sharepoint-controls.com to download latest version of assembly and example of using this control.<br /><br />Additional information on starting a new project is available here: <a href=\"http://www.codeplex.com/Wiki/View.aspx?ProjectName=CodePlex&amp;title=CodePlex%20Project%20Startup%20Guide\">Project Startup Guide</a>.</div><div class=\"ClearBoth\"></div>",
  "TagList": "",
  "LastEdited": "2010-06-13T06:27:42.26-07:00"
}