{
  "ProjectName": "WP7BingMapsCloudMade",
  "Title": "Windows Phone 7 Bing Maps CloudMade TileSource Sample",
  "Description": "This project is designed to be a sample of how you can use Custom map tiles provided by CloudMade.com in the Bing Maps Windows Phone 7 Control. \n\nThis give you the benefit of using one of the many thousands of pre created map styles at CloudMade.com or creating your own map style",
  "MovedLink": "",
  "HomeWiki": "<div class=\"wikidoc\"><b>Project Description</b><br />This project is designed to be a sample of how you can use Custom map tiles provided by CloudMade.com in the Bing Maps Windows Phone 7 Control. <br /><br />This give you the benefit of using one of the many thousands of pre created map styles at CloudMade.com or creating your own map style<br /><br /></div><div class=\"ClearBoth\"></div>",
  "TagList": "Windows Phone 7,Bing Maps,Silverlight,CloudMade,tiles,",
  "LastEdited": "2011-01-20T05:56:03.91-08:00"
}