{
  "ProjectName": "wpfext",
  "Title": ".NET Zen WPF Extensions",
  "Description": "[News Feeds]\n!! .NET Zen WPF Extensions\n_Extensions for WPF by Omer van Kloeten_\n\nMends bugs, adds features and specializations to WPF.\n\nQuestions? Go to [url:http://weblogs.asp.net/OKloeten/Contact.aspx].",
  "MovedLink": "",
  "HomeWiki": "<div class=\"wikidoc\"><a href=\"https://wpfext.codeplex.com/wikipage?title=News%20Feeds&referringTitle=Home\">News Feeds</a>\n<h2>.NET Zen WPF Extensions</h2>\r<i>Extensions for WPF by Omer van Kloeten</i><br /><br />Mends bugs, adds features and specializations to WPF.<br /><br />Questions? Go to <a href=\"http://weblogs.asp.net/OKloeten/Contact.aspx\">http://weblogs.asp.net/OKloeten/Contact.aspx</a>.</div><div class=\"ClearBoth\"></div>",
  "TagList": "wpf,",
  "LastEdited": "2007-12-12T04:13:21.097-08:00"
}